[
  {
    "ContainingType": "ApexApi.Controllers.AdvisorController",
    "Method": "GetAdvisors",
    "RelativePath": "api/Advisor/GetAdvisors",
    "HttpMethod": "GET",
    "IsController": true,
    "Order": 0,
    "Parameters": [],
    "ReturnTypes": []
  },
  {
    "ContainingType": "ApexApi.Controllers.AuthenticateController",
    "Method": "Login",
    "RelativePath": "api/Authenticate/login",
    "HttpMethod": "POST",
    "IsController": true,
    "Order": 0,
    "Parameters": [
      {
        "Name": "model",
        "Type": "ApexApi.Models.LoginModel",
        "IsRequired": true
      }
    ],
    "ReturnTypes": []
  },
  {
    "ContainingType": "ApexApi.Controllers.AuthenticateController",
    "Method": "Register",
    "RelativePath": "api/Authenticate/register",
    "HttpMethod": "POST",
    "IsController": true,
    "Order": 0,
    "Parameters": [
      {
        "Name": "model",
        "Type": "ApexApi.Models.RegisterModel",
        "IsRequired": true
      }
    ],
    "ReturnTypes": []
  },
  {
    "ContainingType": "ApexApi.Controllers.AuthenticateController",
    "Method": "RegisterAdmin",
    "RelativePath": "api/Authenticate/register-admin",
    "HttpMethod": "POST",
    "IsController": true,
    "Order": 0,
    "Parameters": [
      {
        "Name": "model",
        "Type": "ApexApi.Models.RegisterModel",
        "IsRequired": true
      }
    ],
    "ReturnTypes": []
  }
]